varakumar1105_add_numbers/setup.py
varakumar1105_add_numbers.egg-info/PKG-INFO
varakumar1105_add_numbers.egg-info/SOURCES.txt
varakumar1105_add_numbers.egg-info/dependency_links.txt
varakumar1105_add_numbers.egg-info/not-zip-safe
varakumar1105_add_numbers.egg-info/top_level.txt