Metadata-Version: 1.0
Name: varakumar1105-add-numbers
Version: 0.3
Summary: Sample to add two numbers
Home-page: https://github.com/varakumar1105/varakumar1105_add_numbers
Author: VaraKumarJagarapu
Author-email: vignesh.varakumar@gmail.com
License: MIT
Platform: UNKNOWN
